[
  {
    "link": "https://spb.hh.ru/vacancy/77871173?from=vacancy_search_list&query=python",
    "salary": "от 90 000 до 150 000 руб. на руки",
    "company": "ООО Единая Информационная Система ЖКХ ",
    "city": "Санкт-Петербург, Тарасова улица, 12/18"
  },
  {
    "link": "https://spb.hh.ru/vacancy/70705466?from=vacancy_search_list&query=python",
    "salary": "от 60 000 до 220 000 руб. на руки",
    "company": "ООО Фабрика Решений ",
    "city": "Москва, Домодедовская, Шипиловская улица, 28А"
  },
  {
    "link": "https://spb.hh.ru/vacancy/77716464?from=vacancy_search_list&query=python",
    "salary": "от 180 000 руб. на руки",
    "company": "WorkinGeeks ",
    "city": "Санкт-Петербург, Выборгская, Выборгская набережная, 49Б"
  },
  {
    "link": "https://spb.hh.ru/vacancy/77716464?from=vacancy_search_list&query=python",
    "salary": "от 180 000 руб. на руки",
    "company": "WorkinGeeks ",
    "city": "Москва, Кузнецкий мост, Лубянка, Трубная, Малый Кисельный переулок, 1/9"
  },
  {
    "link": "https://spb.hh.ru/vacancy/78106381?from=vacancy_search_list&query=python",
    "salary": "до 8 000 USD до вычета налогов",
    "company": "Apostro ",
    "city": "Москва, Западный административный округ, Можайский район, Инновационный центр Сколково, улица Нобеля, 5"
  },
  {
    "link": "https://spb.hh.ru/vacancy/78140525?from=vacancy_search_list&query=python",
    "salary": "от 150 000 руб. на руки",
    "company": "ООО 24Н Софт ",
    "city": "Брест, Пионерская улица, 52"
  }
]